tptq/feacomposer/__init__.py
tptq/feacomposer/utils.py
tptq_feacomposer-1.11.6.dist-info/WHEEL
tptq_feacomposer-1.11.6.dist-info/METADATA
tptq_feacomposer-1.11.6.dist-info/RECORD
