Metadata-Version: 2.3
Name: tptq-feacomposer
Version: 1.11.6
Summary: A feaLib wrapper for composing FEA code in Python
Author: Liang Hai
Author-email: Liang Hai <liang@typotheque.com>
License: MIT
Requires-Dist: fonttools>=4.43.0
Requires-Python: >=3.10
Project-URL: releasenotes, https://github.com/typotheque/feacomposer/releases
Project-URL: repository, https://github.com/typotheque/feacomposer
